indexmaker/__init__.py
indexmaker/indexmaker_gui.py
indexmaker/indexmaker_script.py
indexmaker-0.2.2.dist-info/METADATA
indexmaker-0.2.2.dist-info/WHEEL
indexmaker-0.2.2.dist-info/entry_points.txt
indexmaker-0.2.2.dist-info/RECORD
